plankode/__init__.py
plankode-0.0.0a0.dist-info/licenses/LICENSE
plankode-0.0.0a0.dist-info/METADATA
plankode-0.0.0a0.dist-info/WHEEL
plankode-0.0.0a0.dist-info/top_level.txt
plankode-0.0.0a0.dist-info/RECORD
