Metadata-Version: 2.4
Name: plankode
Version: 0.0.0a0
Summary: Unified Token Rendering Library for DeepSeek Models.
Author: Plankode Contributors
License-Expression: MIT
Keywords: Tokenization,Transformers,Large Language Models,Natural Language Processing,Artificial Intelligence,LLM,NLP,AI
Classifier: Development Status :: 4 - Beta
Classifier: Programming Language :: Python :: 3
Classifier: Programming Language :: Python :: 3.10
Classifier: Programming Language :: Python :: 3.11
Classifier: Programming Language :: Python :: 3.12
Classifier: Programming Language :: Python :: 3.13
Classifier: Programming Language :: Python :: 3.14
Classifier: Programming Language :: Python :: Implementation :: CPython
Classifier: Operating System :: Microsoft :: Windows
Classifier: Operating System :: POSIX :: Linux
Classifier: Operating System :: MacOS
Classifier: Intended Audience :: Developers
Classifier: Intended Audience :: Education
Classifier: Intended Audience :: Science/Research
Classifier: Topic :: Utilities
Requires-Python: >=3.10
License-File: LICENSE
Requires-Dist: typing-extensions>=4.6.0
Dynamic: license-file
